solution_efe_client_mailing/__init__.py
solution_efe_client_mailing/mailingService.py
solution_efe_client_mailing-1.0.2.dist-info/METADATA
solution_efe_client_mailing-1.0.2.dist-info/WHEEL
solution_efe_client_mailing-1.0.2.dist-info/top_level.txt
solution_efe_client_mailing-1.0.2.dist-info/RECORD
